Metadata-Version: 2.1
Name: DataPdf
Version: 0.0.1
Summary: Traduzir paginas de um pdf e leitura do arquivo com voz do sistema
Home-page: UNKNOWN
Author: Francisco Aparicio & Pedro Tercio
Author-email: faparicionc1996@gmail.com
License: MIT License
Keywords: Pdf
Platform: UNKNOWN
